netflow2json/__init__.py
netflow2json/analyser.py
netflow2json/tools.py
netflow2json/traffic.py
netflow2json/web.py
netflow2json-0.0.2.dist-info/LICENSE
netflow2json-0.0.2.dist-info/METADATA
netflow2json-0.0.2.dist-info/WHEEL
netflow2json-0.0.2.dist-info/top_level.txt
netflow2json-0.0.2.dist-info/RECORD
