Metadata-Version: 2.1
Name: netflow2json
Version: 0.0.2
Summary: This is a Python-based solution for collecting and analyzing Netflow V9 traffic data.
Home-page: https://github.com/h-haghpanah/Netflow_V9_Traffic_Analysis.git
Author: Hesam Haghpanah
Author-email: h.haghpanah@outlook.com
Project-URL: Bug Tracker, https://github.com/h-haghpanah/Netflow_V9_Traffic_Analysis/issues
Classifier: Programming Language :: Python :: 3
Classifier: License :: OSI Approved :: MIT License
Classifier: Operating System :: OS Independent
Requires-Python: >=3.6
License-File: LICENSE
Requires-Dist: flask >=3.0.0
Requires-Dist: netaddr >=0.8.0
Requires-Dist: netflow >=0.12.2
